Metadata-Version: 2.1
Name: django-http-cache-control-view
Version: 2020.7.1
Summary: Django http Cache-Control header view mixin
Home-page: https://github.com/andrewp-as-is/django-http-cache-control-view.py
License: Unlicense
Keywords: django cache-control header view
Platform: UNKNOWN
Classifier: Framework :: Django
Classifier: License :: Public Domain
Classifier: Operating System :: OS Independent
Classifier: Programming Language :: Python :: 3
